helpful_pys/__init__.py
helpful_pys/creds.py.sample
helpful_pys/helper.py
helpful_pys-0.2.1.dist-info/METADATA
helpful_pys-0.2.1.dist-info/WHEEL
helpful_pys-0.2.1.dist-info/top_level.txt
helpful_pys-0.2.1.dist-info/RECORD
