Metadata-Version: 2.2
Name: helpful-pys
Version: 0.2.1
Summary: A helper package to use common functions
Home-page: https://github.com/Gusto/helpful-pys
Author: Lawrence Chin
Author-email: lawrence.chin@gusto.com
License: MIT
Classifier: Programming Language :: Python :: 3
Classifier: License :: OSI Approved :: MIT License
Classifier: Operating System :: OS Independent
Requires-Python: >=3.10
Requires-Dist: redshift_connector>=2.1.3
Requires-Dist: pandas>=2.2.3
Requires-Dist: gspread>=6.1.3
Dynamic: author
Dynamic: author-email
Dynamic: classifier
Dynamic: description
Dynamic: description-content-type
Dynamic: home-page
Dynamic: license
Dynamic: requires-dist
Dynamic: requires-python
Dynamic: summary
